docsgen/__init__.py
docsgen/cli.py
docsgen/docsgen.py
docsgen-0.0.2.dist-info/METADATA
docsgen-0.0.2.dist-info/WHEEL
docsgen-0.0.2.dist-info/entry_points.txt
docsgen-0.0.2.dist-info/top_level.txt
docsgen-0.0.2.dist-info/RECORD
