Metadata-Version: 2.1
Name: docsgen
Version: 0.0.2
Summary: DocsGen is a Python library that generates docs for python libs.
Home-page: https://github.com/IceBytes/DocsGen/
Author: Just Ice
Author-email: MrAws.developer@gmail.com
Project-URL: Source, https://github.com/IceBytes/DocsGen/
Project-URL: Bug Reports, https://github.com/IceBytes/DocsGen/issues
Project-URL: Documentation, https://github.com/IceBytes/DocsGen/
Keywords: Auto docs,Generate docs
Classifier: Development Status :: 1 - Planning
Classifier: Intended Audience :: Developers
Classifier: Programming Language :: Python :: 3
Classifier: Operating System :: Unix
Classifier: Operating System :: MacOS :: MacOS X
Classifier: Operating System :: Microsoft :: Windows
Requires-Dist: docstring-parser
